expand_latex_macros/__init__.py
expand_latex_macros/source.py
expand_latex_macros-2.0.0.dist-info/METADATA
expand_latex_macros-2.0.0.dist-info/WHEEL
expand_latex_macros-2.0.0.dist-info/top_level.txt
expand_latex_macros-2.0.0.dist-info/RECORD
