Metadata-Version: 2.1
Name: expand-latex-macros
Version: 2.0.0
Summary: Removes all user-defined macros in a .tex file and substitutes their definitions back in.
Home-page: UNKNOWN
Author: James McGreivy
Author-email: mcgreivy@mit.edu
License: UNKNOWN
Keywords: latex,LaTeX,macros,\def,\newcommand
Platform: UNKNOWN
Classifier: Programming Language :: Python :: 2
Classifier: Programming Language :: Python :: 3
Classifier: Operating System :: MacOS :: MacOS X
Classifier: Operating System :: Microsoft :: Windows
Requires-Dist: regex
